PyTools_QOL/__init__.py
PyTools_QOL/execution_time.py
PyTools_QOL-0.0.2.dist-info/LICENSE
PyTools_QOL-0.0.2.dist-info/METADATA
PyTools_QOL-0.0.2.dist-info/WHEEL
PyTools_QOL-0.0.2.dist-info/top_level.txt
PyTools_QOL-0.0.2.dist-info/RECORD
