Metadata-Version: 2.1
Name: PyTools_QOL
Version: 0.0.2
Summary: Python tools that I use for quality of life programming
Author-email: Micah Best <micahbest21@gmail.com>
License: MIT License
Project-URL: Homepage, https://github.com/MicahBest/pytools-qol
Project-URL: Issues, https://github.com/MicahBest/pytools-qol/issues
Keywords: tools,quality of life,pytools,pyutils,QOL
Classifier: Programming Language :: Python :: 3
Classifier: License :: OSI Approved :: MIT License
Classifier: Operating System :: OS Independent
Classifier: Intended Audience :: Developers
Requires-Python: >=3.8
License-File: LICENSE
Requires-Dist: numpy >=1.24.0
